bin/__init__.py
bin/cli.py
origocli/__init__.py
origocli/command.py
origocli/date.py
origocli/io.py
origocli/output.py
origocli/commands/__init__.py
origocli/commands/datasets.py
origocli/commands/event_streams.py
origocli/commands/events.py
origocli/commands/status.py
origocli/commands/webhook_tokens.py
origocli/commands/datasets/__init__.py
origocli/commands/datasets/datasets.py
origocli/commands/datasets/wizards.py
origocli/commands/datasets/boilerplate/__init__.py
origocli/commands/datasets/boilerplate/boilerplate.py
origocli/commands/datasets/boilerplate/config.py
origocli/commands/datasets/boilerplate/validator.py
origocli/commands/pipelines/__init__.py
origocli/commands/pipelines/base.py
origocli/commands/pipelines/inputs.py
origocli/commands/pipelines/instances.py
origocli/commands/pipelines/pipelines.py
origocli/commands/pipelines/schemas.py
origocli/data/boilerplate/bin/run.sh
origocli/data/boilerplate/data/hello_world.csv
origocli/data/boilerplate/dataset/dataset-version-edition.json
origocli/data/boilerplate/dataset/dataset-version.json
origocli/data/boilerplate/dataset/dataset.json
origocli/data/boilerplate/pipeline/pipeline-input.json
origocli/data/boilerplate/pipeline/csv-to-parquet/pipeline.json
origocli/data/boilerplate/pipeline/data-copy/pipeline.json
origocli/data/output-format/datasets_config.json
origocli/data/output-format/datasets_copy_file_config.json
origocli/data/output-format/datasets_copy_file_config_2.json
origocli/data/output-format/datasets_dataset_access_check_config.json
origocli/data/output-format/datasets_dataset_access_create_config.json
origocli/data/output-format/datasets_dataset_config.json
origocli/data/output-format/datasets_dataset_version_config.json
origocli/data/output-format/datasets_dataset_version_edition_config.json
origocli/data/output-format/datasets_dataset_version_edition_distributions_config.json
origocli/data/output-format/datasets_dataset_versions_config.json
origo_cli-0.6.0.dist-info/LICENSE
origo_cli-0.6.0.dist-info/METADATA
origo_cli-0.6.0.dist-info/WHEEL
origo_cli-0.6.0.dist-info/entry_points.txt
origo_cli-0.6.0.dist-info/top_level.txt
origo_cli-0.6.0.dist-info/RECORD
