Metadata-Version: 2.1
Name: origo-cli
Version: 0.6.0
Summary: CLI for services provided by Oslo Origo
Home-page: https://github.com/oslokommune/origo-cli/
Author: Oslo Origo
Author-email: dataplattform@oslo.kommune.no
License: MIT
Platform: UNKNOWN
Classifier: Development Status :: 3 - Alpha
Classifier: Programming Language :: Python :: 3
Classifier: License :: OSI Approved :: MIT License
Classifier: Operating System :: OS Independent
Requires-Dist: PrettyTable
Requires-Dist: Sphinx
Requires-Dist: docopt
Requires-Dist: inquirer
Requires-Dist: origo-sdk-python (>=0.3.0)
Requires-Dist: pygments
Requires-Dist: recommonmark
Requires-Dist: requests
Requires-Dist: questionary
